{
    "$schema": "http://json-schema.org/draft-07/schema#",
    "type": "object",
    "title": "Sensor Event Type",
    "properties": {
        "sensor event type id": {
            "type": "number"
        },
        "sensor event type name": {
            "type": "string"
        },
        "sensor event type description": {
            "type": "string"
        }
    },
    "additionalProperties": false,
    "required": [
        "sensor event type id",
        "sensor event type name"
    ]
}